beans_logging_fastapi/__init__.py
beans_logging_fastapi/__version__.py
beans_logging_fastapi/_async_log.py
beans_logging_fastapi/_base.py
beans_logging_fastapi/_filters.py
beans_logging_fastapi/_formats.py
beans_logging_fastapi/_handlers.py
beans_logging_fastapi/_middlewares.py
beans_logging_fastapi-2.0.0.dist-info/licenses/LICENSE.txt
beans_logging_fastapi-2.0.0.dist-info/METADATA
beans_logging_fastapi-2.0.0.dist-info/WHEEL
beans_logging_fastapi-2.0.0.dist-info/top_level.txt
beans_logging_fastapi-2.0.0.dist-info/RECORD
