Metadata-Version: 2.4
Name: beans_logging_fastapi
Version: 2.0.0
Summary: This is a middleware for FastAPI HTTP access logs. It is based on 'beans-logging' package.
Author-email: Batkhuu Byambajav <batkhuu10@gmail.com>
Project-URL: Homepage, https://github.com/bybatkhuu/module-fastapi-logging
Project-URL: Documentation, https://fastapi-logging-docs.bybatkhuu.dev
Project-URL: Repository, https://github.com/bybatkhuu/module-fastapi-logging.git
Project-URL: Issues, https://github.com/bybatkhuu/module-fastapi-logging/issues
Project-URL: Changelog, https://github.com/bybatkhuu/module-fastapi-logging/blob/main/CHANGELOG.md
Keywords: beans_logging_fastapi,fastapi-logging,fastapi-logging-middleware,fastapi-middleware,logging-middleware,middleware,beans-logging,http-access-logging,logging,logger,loguru
Classifier: Development Status :: 4 - Beta
Classifier: Intended Audience :: Developers
Classifier: Topic :: Software Development :: Libraries
Classifier: Operating System :: OS Independent
Classifier: Programming Language :: Python :: 3
Classifier: Programming Language :: Python :: 3.10
Classifier: Programming Language :: Python :: 3.11
Classifier: Programming Language :: Python :: 3.12
Classifier: Programming Language :: Python :: 3.13
Requires-Python: <4.0,>=3.10
License-File: LICENSE.txt
Requires-Dist: fastapi<1.0.0,>=0.99.1
Requires-Dist: beans-logging<8.0.0,>=7.1.0
Provides-Extra: test
Requires-Dist: pytest<10.0.0,>=8.0.2; extra == "test"
Requires-Dist: pytest-cov<8.0.0,>=5.0.0; extra == "test"
Requires-Dist: pytest-xdist<4.0.0,>=3.6.1; extra == "test"
Requires-Dist: pytest-benchmark<6.0.0,>=5.0.1; extra == "test"
Provides-Extra: build
Requires-Dist: setuptools<81.0.0,>=70.3.0; extra == "build"
Requires-Dist: wheel<1.0.0,>=0.43.0; extra == "build"
Requires-Dist: build<2.0.0,>=1.1.1; extra == "build"
Requires-Dist: twine<7.0.0,>=6.0.1; extra == "build"
Provides-Extra: docs
Requires-Dist: pylint<5.0.0,>=3.0.4; extra == "docs"
Requires-Dist: mkdocs-material<10.0.0,>=9.5.50; extra == "docs"
Requires-Dist: mkdocs-awesome-nav<4.0.0,>=3.0.0; extra == "docs"
Requires-Dist: mkdocstrings[python]<2.0.0,>=0.24.3; extra == "docs"
Requires-Dist: mike<3.0.0,>=2.1.3; extra == "docs"
Provides-Extra: dev
Requires-Dist: pytest<10.0.0,>=8.0.2; extra == "dev"
Requires-Dist: pytest-cov<8.0.0,>=5.0.0; extra == "dev"
Requires-Dist: pytest-xdist<4.0.0,>=3.6.1; extra == "dev"
Requires-Dist: pytest-benchmark<6.0.0,>=5.0.1; extra == "dev"
Requires-Dist: setuptools<81.0.0,>=70.3.0; extra == "dev"
Requires-Dist: wheel<1.0.0,>=0.43.0; extra == "dev"
Requires-Dist: build<2.0.0,>=1.1.1; extra == "dev"
Requires-Dist: twine<7.0.0,>=6.0.1; extra == "dev"
Requires-Dist: pylint<5.0.0,>=3.0.4; extra == "dev"
Requires-Dist: mkdocs-material<10.0.0,>=9.5.50; extra == "dev"
Requires-Dist: mkdocs-awesome-nav<4.0.0,>=3.0.0; extra == "dev"
Requires-Dist: mkdocstrings[python]<2.0.0,>=0.24.3; extra == "dev"
Requires-Dist: mike<3.0.0,>=2.1.3; extra == "dev"
Requires-Dist: pyright<2.0.0,>=1.1.392; extra == "dev"
Requires-Dist: pre-commit<5.0.0,>=4.0.1; extra == "dev"
Dynamic: license-file
